opencloning_linkml/__init__.py
opencloning_linkml/_version.py
opencloning_linkml/datamodel/__init__.py
opencloning_linkml/datamodel/_models.py
opencloning_linkml/datamodel/models.py
opencloning_linkml/migrations/__init__.py
opencloning_linkml/migrations/migrate.py
opencloning_linkml/migrations/model_archive/v0_2_6_1.py
opencloning_linkml/migrations/model_archive/v0_2_8.py
opencloning_linkml/migrations/model_archive/v0_2_9.py
opencloning_linkml/migrations/model_archive/v0_4_0.py
opencloning_linkml/migrations/model_archive/v0_4_6.py
opencloning_linkml/migrations/model_archive/v0_4_9.py
opencloning_linkml/migrations/transformations/v0_2_6_1_to_v_0_2_8.py
opencloning_linkml/migrations/transformations/v0_2_8_to_v0_2_9.py
opencloning_linkml/migrations/transformations/v0_2_9_to_v_0_4_0.py
opencloning_linkml/migrations/transformations/v0_4_0_to_v0_4_6.py
opencloning_linkml/migrations/transformations/v0_4_6_to_v0_4_9.py
opencloning_linkml/schema/opencloning_linkml.yaml
opencloning_linkml-0.4.9.dist-info/METADATA
opencloning_linkml-0.4.9.dist-info/WHEEL
opencloning_linkml-0.4.9.dist-info/licenses/LICENSE
opencloning_linkml-0.4.9.dist-info/RECORD
