Metadata-Version: 2.4
Name: opencloning-linkml
Version: 0.4.9
Summary: A LinkML data model for OpenCloning
License: MIT
License-File: LICENSE
Author: Manuel Lera-Ramirez
Author-email: manuel.lera-ramirez@ucl.ac.uk
Requires-Python: >=3.10,<4.0
Classifier: Development Status :: 3 - Alpha
Classifier: Intended Audience :: Developers
Classifier: License :: OSI Approved :: MIT License
Classifier: Programming Language :: Python :: 3
Classifier: Programming Language :: Python :: 3.10
Classifier: Programming Language :: Python :: 3.11
Classifier: Programming Language :: Python :: 3.12
Classifier: Programming Language :: Python :: 3.13
Classifier: Programming Language :: Python :: 3.14
Classifier: Programming Language :: Python :: 3.9
Provides-Extra: docs
Requires-Dist: linkml (>=1.9.2,<2.0.0) ; extra == "docs"
Requires-Dist: pydantic (>=2.7.1,<3.0.0)
Project-URL: Documentation, https://genestorian.github.io/OpenCloning_LinkML
Project-URL: Homepage, https://github.com/genestorian/OpenCloning_LinkML
Project-URL: Repository, https://github.com/genestorian/OpenCloning_LinkML
